llm_rs/__init__.py
llm_rs/auto.py
llm_rs/base_model.py
llm_rs/config.pyi
llm_rs/llm_rs.cp310-win_amd64.pyd
llm_rs/llm_rs.pyi
llm_rs/models.pyi
llm_rs/py.typed
llm_rs/repository.py
llm_rs/results.pyi
llm_rs/convert/__init__.py
llm_rs/convert/auto_converter.py
llm_rs/convert/models/__init__.py
llm_rs/convert/models/_base.py
llm_rs/convert/models/bloom.py
llm_rs/convert/models/gpt2.py
llm_rs/convert/models/gptj.py
llm_rs/convert/models/gptneox.py
llm_rs/convert/models/llama.py
llm_rs/convert/models/mpt.py
llm_rs/haystack/__init__.py
llm_rs/langchain/__init__.py
llm_rs/langchain/langchain.py
llm_rs_cuda-0.0.1.dist-info/LICENSE
llm_rs_cuda-0.0.1.dist-info/METADATA
llm_rs_cuda-0.0.1.dist-info/WHEEL
llm_rs_cuda-0.0.1.dist-info/top_level.txt
llm_rs_cuda-0.0.1.dist-info/RECORD
