Metadata-Version: 2.1
Name: llm-rs-cuda
Version: 0.0.1
Summary: Unofficial python bindings for llm-rs.
Author: Lukas Kreussel
Project-URL: repository, https://github.com/LLukas22/llm-rs-python
Project-URL: documentation, https://llukas22.github.io/llm-rs-python/
Keywords: LLM,Transformers
Classifier: Programming Language :: Rust
Classifier: Programming Language :: Python :: Implementation :: CPython
Classifier: Programming Language :: Python :: Implementation :: PyPy
Classifier: Programming Language :: Python :: 3
Classifier: License :: OSI Approved :: MIT License
Requires-Python: >=3.7
License-File: LICENSE
Requires-Dist: blake3
Requires-Dist: huggingface-hub (>=0.14.1)
Provides-Extra: convert
Requires-Dist: transformers (>=4.29.0) ; extra == 'convert'
Requires-Dist: sentencepiece (>=0.1.99) ; extra == 'convert'
Requires-Dist: torch (>=2.0.0) ; extra == 'convert'
Requires-Dist: accelerate (>=0.19.0) ; extra == 'convert'
Requires-Dist: tqdm ; extra == 'convert'
Requires-Dist: einops (>=0.6.1) ; extra == 'convert'
Provides-Extra: langchain
Requires-Dist: langchain (>=0.0.190) ; extra == 'langchain'
